[
  {
    "id": "math_001",
    "exam": "JEE",
    "subject": "Mathematics",
    "question": "If sin θ = 3/5, then cos θ is:",
    "options": {"A": "4/5", "B": "5/4", "C": "1/5", "D": "√3/2"},
    "answer": "A"
  },
  {
    "id": "math_002",
    "exam": "NEET",
    "subject": "Mathematics",
    "question": "The derivative of e^x is:",
    "options": {"A": "1", "B": "x e^x", "C": "e^x", "D": "ln(x)"},
    "answer": "C"
  },
  {
    "id": "math_003",
    "exam": "JEE",
    "subject": "Mathematics",
    "question": "If A = {1,2,3} and B = {a,b}, then the number of relations from A to B is:",
    "options": {"A": "64", "B": "32", "C": "16", "D": "8"},
    "answer": "A"
  },
  {
    "id": "math_004",
    "exam": "NEET",
    "subject": "Mathematics",
    "question": "The sum of first n natural numbers is:",
    "options": {"A": "n(n+1)/2", "B": "n²", "C": "n(n-1)/2", "D": "2n+1"},
    "answer": "A"
  },
  {
    "id": "math_005",
    "exam": "JEE",
    "subject": "Mathematics",
    "question": "The value of lim(x→0) (sin x / x) is:",
    "options": {"A": "0", "B": "1", "C": "∞", "D": "Does not exist"},
    "answer": "B"
  },
  {
    "id": "math_006",
    "exam": "JEE",
    "subject": "Mathematics",
    "question": "The probability of getting a head when a coin is tossed once is:",
    "options": {"A": "1/4", "B": "1/3", "C": "1/2", "D": "1"},
    "answer": "C"
  },
  {
    "id": "math_007",
    "exam": "JEE",
    "subject": "Mathematics",
    "question": "If logₐ(b) = c, then b equals:",
    "options": {"A": "a^c", "B": "c^a", "C": "log(a+c)", "D": "a/c"},
    "answer": "A"
  },
  {
    "id": "math_008",
    "exam": "NEET",
    "subject": "Mathematics",
    "question": "The slope of line 2x + 3y = 5 is:",
    "options": {"A": "-2/3", "B": "2/3", "C": "-3/2", "D": "3/2"},
    "answer": "A"
  },
  {
    "id": "math_009",
    "exam": "JEE",
    "subject": "Mathematics",
    "question": "The distance between (1,2) and (4,6) is:",
    "options": {"A": "5", "B": "4", "C": "3", "D": "2"},
    "answer": "A"
  },
  {
    "id": "math_010",
    "exam": "JEE",
    "subject": "Mathematics",
    "question": "The sum of the roots of x² - 5x + 6 = 0 is:",
    "options": {"A": "5", "B": "6", "C": "-5", "D": "-6"},
    "answer": "A"
  },
  {
    "id": "math_011",
    "exam": "JEE",
    "subject": "Mathematics",
    "question": "The general solution of sin x = 0 is:",
    "options": {"A": "nπ", "B": "π/2 + nπ", "C": "2nπ", "D": "None"},
    "answer": "A"
  },
  {
    "id": "math_012",
    "exam": "JEE",
    "subject": "Mathematics",
    "question": "If tan A = 1, then A is:",
    "options": {"A": "π/4", "B": "π/2", "C": "π", "D": "0"},
    "answer": "A"
  },
  {
    "id": "math_013",
    "exam": "JEE",
    "subject": "Mathematics",
    "question": "The 10th term of an AP with first term 2 and common difference 3 is:",
    "options": {"A": "29", "B": "30", "C": "28", "D": "31"},
    "answer": "A"
  },
  {
    "id": "math_014",
    "exam": "JEE",
    "subject": "Mathematics",
    "question": "If the nth term of an AP is 3n+2, then the first term is:",
    "options": {"A": "5", "B": "2", "C": "3", "D": "1"},
    "answer": "A"
  },
  {
    "id": "math_015",
    "exam": "JEE",
    "subject": "Mathematics",
    "question": "The sum of infinite GP with first term 2 and ratio 1/2 is:",
    "options": {"A": "4", "B": "2", "C": "1", "D": "∞"},
    "answer": "A"
  },
  {
    "id": "math_016",
    "exam": "JEE",
    "subject": "Mathematics",
    "question": "If the determinant of [[a, b], [c, d]] is 0, then:",
    "options": {"A": "ad - bc = 0", "B": "ab - cd = 0", "C": "a+d=0", "D": "a=b=c=d"},
    "answer": "A"
  },
  {
    "id": "math_017",
    "exam": "NEET",
    "subject": "Mathematics",
    "question": "The mean of first 5 natural numbers is:",
    "options": {"A": "3", "B": "2.5", "C": "5", "D": "4"},
    "answer": "A"
  },
  {
    "id": "math_018",
    "exam": "JEE",
    "subject": "Mathematics",
    "question": "Variance is always:",
    "options": {"A": "Positive", "B": "Negative", "C": "Zero or positive", "D": "Zero or negative"},
    "answer": "C"
  },
  {
    "id": "math_019",
    "exam": "JEE",
    "subject": "Mathematics",
    "question": "The probability of getting sum 7 on two dice is:",
    "options": {"A": "1/6", "B": "1/12", "C": "1/36", "D": "5/36"},
    "answer": "A"
  },
  {
    "id": "math_020",
    "exam": "NEET",
    "subject": "Mathematics",
    "question": "The integration of cos x is:",
    "options": {"A": "sin x + C", "B": "-sin x + C", "C": "cos x + C", "D": "tan x + C"},
    "answer": "A"
  },
  {
    "id": "math_021",
    "exam": "JEE",
    "subject": "Mathematics",
    "question": "The integration of 1/x is:",
    "options": {"A": "ln|x| + C", "B": "1/x + C", "C": "e^x + C", "D": "x + C"},
    "answer": "A"
  },
  {
    "id": "math_022",
    "exam": "JEE",
    "subject": "Mathematics",
    "question": "The derivative of ln x is:",
    "options": {"A": "1/x", "B": "ln(x)", "C": "x ln(x)", "D": "x"},
    "answer": "A"
  },
  {
    "id": "math_023",
    "exam": "JEE",
    "subject": "Mathematics",
    "question": "The coordinates of centroid of triangle with vertices (0,0), (6,0), (0,6) are:",
    "options": {"A": "(2,2)", "B": "(3,3)", "C": "(4,4)", "D": "(6,6)"},
    "answer": "B"
  },
  {
    "id": "math_024",
    "exam": "JEE",
    "subject": "Mathematics",
    "question": "Equation of circle with center (0,0) and radius 5 is:",
    "options": {"A": "x² + y² = 25", "B": "x² + y² = 5", "C": "x² + y² - 25 = 0", "D": "Both A and C"},
    "answer": "D"
  },
  {
    "id": "math_025",
    "exam": "NEET",
    "subject": "Mathematics",
    "question": "If sin²x + cos²x = ?",
    "options": {"A": "1", "B": "0", "C": "2", "D": "None"},
    "answer": "A"
  },
  {
    "id": "math_026",
    "exam": "JEE",
    "subject": "Mathematics",
    "question": "If n(A)=10, n(B)=15, n(A∪B)=20, then n(A∩B) = ?",
    "options": {"A": "5", "B": "10", "C": "15", "D": "20"},
    "answer": "A"
  },
  {
    "id": "math_027",
    "exam": "JEE",
    "subject": "Mathematics",
    "question": "If a matrix has order 2x3, it has how many elements?",
    "options": {"A": "5", "B": "6", "C": "8", "D": "9"},
    "answer": "B"
  },
  {
    "id": "math_028",
    "exam": "NEET",
    "subject": "Mathematics",
    "question": "The binomial expansion of (x+y)² has how many terms?",
    "options": {"A": "2", "B": "3", "C": "4", "D": "5"},
    "answer": "B"
  },
  {
    "id": "math_029",
    "exam": "JEE",
    "subject": "Mathematics",
    "question": "nPr / nCr = ?",
    "options": {"A": "r!", "B": "n!", "C": "(n-r)!", "D": "None"},
    "answer": "A"
  },
  {
    "id": "math_030",
    "exam": "JEE",
    "subject": "Mathematics",
    "question": "If f(x)=x², then f'(x) is:",
    "options": {"A": "2x", "B": "x", "C": "x²", "D": "1"},
    "answer": "A"
  }
]
